deposit/__init__.py
deposit/_meta.py
deposit/_version.py
deposit/datasource/__init__.py
deposit/datasource/abstract_datasource.py
deposit/datasource/abstract_dbsource.py
deposit/datasource/abstract_filesource.py
deposit/datasource/db.py
deposit/datasource/db_rel.py
deposit/datasource/json.py
deposit/datasource/memory.py
deposit/datasource/pickle.py
deposit/externalsource/__init__.py
deposit/externalsource/abstract_externalsource.py
deposit/externalsource/csv.py
deposit/externalsource/shp.py
deposit/externalsource/xlsx.py
deposit/query/__init__.py
deposit/query/parse.py
deposit/query/query.py
deposit/store/__init__.py
deposit/store/abstract_delement.py
deposit/store/abstract_dtype.py
deposit/store/dclass.py
deposit/store/ddatetime.py
deposit/store/ddict.py
deposit/store/dgeometry.py
deposit/store/dgraph.py
deposit/store/dobject.py
deposit/store/dresource.py
deposit/store/store.py
deposit/utils/__init__.py
deposit/utils/fnc_files.py
deposit/utils/fnc_geometry.py
deposit/utils/fnc_get_linked_objects.py
deposit/utils/fnc_serialize.py
deposit-1.6.36.dist-info/LICENSE
deposit-1.6.36.dist-info/METADATA
deposit-1.6.36.dist-info/WHEEL
deposit-1.6.36.dist-info/top_level.txt
deposit-1.6.36.dist-info/RECORD
