Metadata-Version: 2.1
Name: deposit
Version: 1.6.36
Summary: Graph database for scientific data collection
Author-email: Peter Demján <peter.demjan@gmail.com>
License: GNU General Public License v3 (GPLv3)
Project-URL: homepage, https://github.com/demjanp/deposit
Keywords: database,graph
Classifier: Development Status :: 5 - Production/Stable
Classifier: Intended Audience :: Science/Research
Classifier: Topic :: Database
Classifier: License :: OSI Approved :: GNU General Public License v3 (GPLv3)
Classifier: Programming Language :: Python :: 3.10
Classifier: Operating System :: Microsoft :: Windows :: Windows 10
Requires-Python: <4,>=3.10
License-File: LICENSE
Requires-Dist: certifi<2025,>=2024.6.2
Requires-Dist: cryptography<43,>=42.0.8
Requires-Dist: natsort<9,>=8.4.0
Requires-Dist: networkit==11.0
Requires-Dist: networkx<4,>=3.3
Requires-Dist: numpy==1.21.3
Requires-Dist: openpyxl<4,>=3.1.5
Requires-Dist: pandas==2.0.3
Requires-Dist: Pillow<11,>=10.4.0
Requires-Dist: pyshp<3,>=2.3.1
Requires-Dist: scipy==1.7.3
Requires-Dist: Shapely<3,==2.0.4
Requires-Dist: Unidecode<2,>=1.3.8
Requires-Dist: validators<1,>=0.29.0
Requires-Dist: psycopg2-binary<3,>=2.9.9; sys_platform == "darwin"
Requires-Dist: psycopg2<3,>=2.9.9; sys_platform == "win32" or sys_platform == "linux" or sys_platform == "linux2"
